napari_file2folder/__init__.py
napari_file2folder/_custom_widgets.py
napari_file2folder/_widget.py
napari_file2folder/napari.yaml
napari_file2folder-0.0.4.dist-info/licenses/LICENSE
napari_file2folder-0.0.4.dist-info/METADATA
napari_file2folder-0.0.4.dist-info/WHEEL
napari_file2folder-0.0.4.dist-info/entry_points.txt
napari_file2folder-0.0.4.dist-info/top_level.txt
napari_file2folder-0.0.4.dist-info/RECORD
